{"cameraMode":{"drawMode":0,"name":"Shaded","section":"Shading Mode"},"sceneLighting":true,"audioPlay":false,"sceneViewState":{"m_AlwaysRefresh":false,"showFog":true,"showSkybox":true,"showFlares":true,"showImageEffects":true,"showParticleSystems":true,"showVisualEffectGraphs":true,"m_FxEnabled":true},"in2DMode":false,"pivot":{"x":-0.46892595291137698,"y":-0.2252507209777832,"z":3.422518730163574},"rotation":{"x":-0.22385236620903016,"y":0.3140174448490143,"z":-0.07645028084516525,"w":-0.9194802641868591},"size":4.795666217803955,"orthographic":false}